llama_deploy/core/__init__.py
llama_deploy/core/_compat.py
llama_deploy/core/client/manage_client.py
llama_deploy/core/client/ssl_util.py
llama_deploy/core/config.py
llama_deploy/core/deployment_config.py
llama_deploy/core/git/git_util.py
llama_deploy/core/iter_utils.py
llama_deploy/core/path_util.py
llama_deploy/core/py.typed
llama_deploy/core/schema/__init__.py
llama_deploy/core/schema/base.py
llama_deploy/core/schema/deployments.py
llama_deploy/core/schema/git_validation.py
llama_deploy/core/schema/projects.py
llama_deploy/core/schema/public.py
llama_deploy/core/server/manage_api/__init__.py
llama_deploy/core/server/manage_api/_abstract_deployments_service.py
llama_deploy/core/server/manage_api/_create_deployments_router.py
llama_deploy/core/server/manage_api/_exceptions.py
llama_deploy/core/ui_build.py
llama_deploy_core-0.4.1.dist-info/WHEEL
llama_deploy_core-0.4.1.dist-info/METADATA
llama_deploy_core-0.4.1.dist-info/RECORD
